AFDCal/__init__.py
AFDCal/_decomposition.py
AFDCal/_initfun.py
AFDCal/_io.py
AFDCal/_logfun.py
AFDCal/_plot.py
AFDCal/_utils.py
Toolbox_for_Adaptive_Fourier_Decomposition-2.1.2.dist-info/METADATA
Toolbox_for_Adaptive_Fourier_Decomposition-2.1.2.dist-info/WHEEL
Toolbox_for_Adaptive_Fourier_Decomposition-2.1.2.dist-info/top_level.txt
Toolbox_for_Adaptive_Fourier_Decomposition-2.1.2.dist-info/RECORD
