Metadata-Version: 2.1
Name: Toolbox-for-Adaptive-Fourier-Decomposition
Version: 2.1.2
Summary: Toolbox of adaptive Fourier decomposition (AFD) for Python.
Home-page: https://github.com/pikipity/Toolbox-for-Adaptive-Fourier-Decomposition
Author: Ze Wang
Author-email: pikipityw@gmail.com
Classifier: Programming Language :: Python :: 3.9
Classifier: Operating System :: OS Independent
Requires-Python: >=3.9
Requires-Dist: numpy<=1.23,>1.0
Requires-Dist: scipy<=1.13,>1.0
Requires-Dist: joblib<=1.4,>1.0
Requires-Dist: matplotlib<=3.8,>3.0
Requires-Dist: mat73<=1.0
